ns_lab_aws/__init__.py
ns_lab_aws/init.py
ns_lab_aws/manager.py
ns_lab_aws/config/__init__.py
ns_lab_aws/config/environment.py
ns_lab_aws/config/libraries.py
ns_lab_aws/config/logging.py
ns_lab_aws/config/settings.py
ns_lab_aws/console/__init__.py
ns_lab_aws/console/client.py
ns_lab_aws/converter/__init__.py
ns_lab_aws/converter/converter.py
ns_lab_aws/services/__init__.py
ns_lab_aws/services/s3buckets.py
ns_lab_aws-23.6.9.post1349.dist-info/METADATA
ns_lab_aws-23.6.9.post1349.dist-info/WHEEL
ns_lab_aws-23.6.9.post1349.dist-info/top_level.txt
ns_lab_aws-23.6.9.post1349.dist-info/RECORD
