Metadata-Version: 2.1
Name: ns-lab-aws
Version: 23.6.9.post1349
Summary: AWS Console Tool
Author-email: Salavat Nigmatullin <salavat@nigmatullin.net>
Project-URL: Homepage, https://github.com/salavatn/Python/tree/main/AWS
Project-URL: Documentation, https://github.com/salavatn/Python/blob/main/AWS/README.md
Project-URL: Changes, https://github.com/salavatn/Python/commits/main/AWS/README.md
Keywords: aws,s3 bucket
Requires-Python: >=3.8
Requires-Dist: boto3 (==1.26.147)
Requires-Dist: botocore (==1.29.147)
Requires-Dist: colorlog (==6.7.0)
Requires-Dist: jmespath (==1.0.1)
Requires-Dist: markdown-it-py (==2.2.0)
Requires-Dist: mdurl (==0.1.2)
Requires-Dist: Pygments (==2.15.1)
Requires-Dist: python-dateutil (==2.8.2)
Requires-Dist: python-dotenv (==1.0.0)
Requires-Dist: rich (==13.4.1)
Requires-Dist: s3transfer (==0.6.1)
Requires-Dist: six (==1.16.0)
Requires-Dist: urllib3 (==1.26.16)
